urmarketscraper/market.py
urmarketscraper/offer.py
urmarketscraper/offer_list.py
urmarketscraper-1.1.0.dist-info/LICENSE
urmarketscraper-1.1.0.dist-info/WHEEL
urmarketscraper-1.1.0.dist-info/METADATA
urmarketscraper-1.1.0.dist-info/RECORD
