Metadata-Version: 2.1
Name: urmarketscraper
Version: 1.1.0
Summary: Collects market offers for Urban Rivals.
Home-page: https://github.com/brentspector/urmarketscraper
License: MIT
Author: Brent Spector
Author-email: brent.spector@yahoo.com
Requires-Python: >=3.8,<4.0
Classifier: License :: OSI Approved :: MIT License
Classifier: Programming Language :: Python :: 3
Classifier: Programming Language :: Python :: 3.8
Requires-Dist: bs4 (>=0.0.1,<0.0.2)
Requires-Dist: requests (>=2.23.0,<3.0.0)
Project-URL: Repository, https://github.com/brentspector/urmarketscraper
